magic_router/__init__.py
fastapi_magic_router-0.2.0.dist-info/METADATA
fastapi_magic_router-0.2.0.dist-info/WHEEL
fastapi_magic_router-0.2.0.dist-info/licenses/LICENSE
fastapi_magic_router-0.2.0.dist-info/RECORD
