Metadata-Version: 2.1
Name: fastapi-magic-router
Version: 0.2.0
Summary: 🪄 FastAPI router with magical powers ✨
Project-URL: Homepage, https://github.com/sayanarijit/fastapi-magic-router
Author-email: Arijit Basu <sayanarijit@gmail.com>
Maintainer-email: Arijit Basu <sayanarijit@gmail.com>
License: MIT License
License-File: LICENSE
Keywords: api,fastapi,rest,router
Classifier: Development Status :: 4 - Beta
Classifier: Intended Audience :: Developers
Classifier: Intended Audience :: Information Technology
Classifier: Intended Audience :: Other Audience
Classifier: License :: OSI Approved :: MIT License
Classifier: Natural Language :: English
Classifier: Programming Language :: Python :: 3
Classifier: Topic :: Software Development
Classifier: Topic :: Software Development :: Libraries
Requires-Python: >=3.10
Requires-Dist: fastapi
